{
  "id": "5.3",
  "region": "france",
  "title": "1 Ajaccio - 2 Porto-Ota - 2 Corte - 2 Bonifacio - 1 Ajaccio",
  "nights": 8,
  "currency": "EUR",
  "winter_only": false,
  "pricing_locked": false,
  "validity": [
    {
      "label": "Winter",
      "start": "2025-11-01",
      "end": "2026-03-31"
    },
    {
      "label": "Summer",
      "start": "2026-04-01",
      "end": "2026-11-30"
    }
  ],
  "hotels": [
    {
      "city": "Ajaccio",
      "nights": 1,
      "hotel_3star": "Holiday Inn Express Ajaccio by IHG",
      "hotel_4star": "Best Western Plus Ajaccio Amiraute",
      "rate_type": "PI",
      "rate_3star": 160,
      "rate_4star": 190,
      "currency": "EUR"
    },
    {
      "city": "Porto-Ota",
      "nights": 2,
      "hotel_3star": "H\u00f4tel Cala di Sole",
      "hotel_4star": "H\u00f4tel Cala di Sole",
      "rate_type": "PI",
      "rate_3star": 260,
      "rate_4star": 260,
      "currency": "EUR"
    },
    {
      "city": "Corte",
      "nights": 2,
      "hotel_3star": "Les Jardins De La Glaciere",
      "hotel_4star": "Les Jardins De La Glaciere",
      "rate_type": "PI",
      "rate_3star": 360,
      "rate_4star": 360,
      "currency": "EUR"
    },
    {
      "city": "Bonifacio",
      "nights": 2,
      "hotel_3star": "Best Western Hotel Du Roy D'aragon",
      "hotel_4star": "Best Western Hotel Du Roy D'aragon",
      "rate_type": "PI",
      "rate_3star": 380,
      "rate_4star": 380,
      "currency": "EUR"
    },
    {
      "city": "Ajaccio",
      "nights": 1,
      "hotel_3star": "Holiday Inn Express Ajaccio by IHG",
      "hotel_4star": "Best Western Plus Ajaccio Amiraute",
      "rate_type": "PI",
      "rate_3star": 160,
      "rate_4star": 190,
      "currency": "EUR"
    }
  ],
  "variants": {
    "self_drive": {
      "car_hire": {
        "description": "Rental car, Ajaccio airport, round-trip",
        "rate": 650,
        "currency": "EUR"
      },
      "services": [
        {
          "day": "Day 1",
          "description": "Arrive Ajaccio, pickup rental car at airport",
          "rate_type": "PI",
          "rate": 650,
          "currency": "EUR"
        }
      ],
      "day_descriptions": {
        "Day 1": "Arrive Ajaccio and collect your rental car. Napoleon's birthplace has a relaxed Italianate charm \u2014 the covered market, the Place Foch and the citadel are worth an evening stroll. Overnight Ajaccio.",
        "Day 2": "Drive north via the breathtaking Calanques de Piana \u2014 UNESCO-listed orange granite formations above a deep blue sea. Arrive Porto-Ota. Overnight Porto-Ota.",
        "Day 3": "Day at leisure. Optional morning boat tour into the Scandola nature reserve \u2014 only accessible by sea. Overnight Porto-Ota.",
        "Day 4": "Drive inland to Corte via the Gorges de Spelunca and the Col de Vergio mountain pass. Corsica's ancient capital sits above a dramatic gorge. Overnight Corte.",
        "Day 5": "Morning in the Restonica Valley \u2014 glacier pools and mountain walking. Afternoon: Corte's citadel and old town. Overnight Corte.",
        "Day 6": "Drive the east coast to Bonifacio via Aleria and Porto-Vecchio. Bonifacio's old town sits on white limestone cliffs above the Strait of Bonifacio. Evening walk along the ramparts. Overnight Bonifacio.",
        "Day 7": "Day at leisure \u2014 beaches at Palombaggia or Santa Giulia. Optional boat trip to the Lavezzi Islands. Overnight Bonifacio.",
        "Day 8": "Drive back to Ajaccio via Sart\u00e8ne. Overnight Ajaccio.",
        "Day 9": "Proceed to Ajaccio airport. Return rental car."
      },
      "pricing": {
        "Premium": {
          "winter": {
            "date_start": "2025-11-01",
            "date_end": "2026-03-31",
            "3star": {
              "single": 2364.0,
              "twin": 1182.0,
              "child": 491.712
            },
            "4star": {
              "single": 2436.0,
              "twin": 1218.0,
              "child": 506.688
            }
          },
          "summer": {
            "date_start": "2026-04-01",
            "date_end": "2026-11-30",
            "3star": {
              "single": 2462.5,
              "twin": 1231.25,
              "child": 512.2
            },
            "4star": {
              "single": 2537.5,
              "twin": 1268.75,
              "child": 527.8
            }
          }
        },
        "Standard": {
          "winter": {
            "date_start": "2025-11-01",
            "date_end": "2026-03-31",
            "3star": {
              "single": 2167.0,
              "twin": 1083.5,
              "child": 450.736
            },
            "4star": {
              "single": 2233.0,
              "twin": 1116.5,
              "child": 464.464
            }
          },
          "summer": {
            "date_start": "2026-04-01",
            "date_end": "2026-11-30",
            "3star": {
              "single": 2265.5,
              "twin": 1132.75,
              "child": 471.224
            },
            "4star": {
              "single": 2334.5,
              "twin": 1167.25,
              "child": 485.576
            }
          }
        }
      }
    }
  },
  "optionals": [
    {
      "description": "Boat tour Scandola reserve & Calanques de Piana, 3.5 hrs",
      "rate": 72,
      "currency": "EUR"
    },
    {
      "description": "Boat tour Lavezzi Islands & caves, 4 hrs",
      "rate": 98,
      "currency": "EUR"
    },
    {
      "description": "Maison Bonaparte admission (Napoleon's birthplace)",
      "rate": 7,
      "currency": "EUR"
    }
  ],
  "description": "Corsica's dramatic interior \u2014 the Calanques de Piana, Spelunca gorge, Restonica valley and the white limestone cliffs of Bonifacio on a self-drive circuit."
}